vocalinux/__init__.py
vocalinux/common_types.py
vocalinux/main.py
vocalinux/version.py
vocalinux/speech_recognition/__init__.py
vocalinux/speech_recognition/command_processor.py
vocalinux/speech_recognition/recognition_manager.py
vocalinux/text_injection/__init__.py
vocalinux/text_injection/text_injector.py
vocalinux/ui/__init__.py
vocalinux/ui/action_handler.py
vocalinux/ui/audio_feedback.py
vocalinux/ui/config_manager.py
vocalinux/ui/keyboard_shortcuts.py
vocalinux/ui/logging_dialog.py
vocalinux/ui/logging_manager.py
vocalinux/ui/settings_dialog.py
vocalinux/ui/tray_indicator.py
vocalinux/utils/__init__.py
vocalinux/utils/resource_manager.py
vocalinux-0.3.0a0.data/data/share/applications/vocalinux.desktop
vocalinux-0.3.0a0.data/data/share/icons/hicolor/scalable/apps/vocalinux-microphone-off.svg
vocalinux-0.3.0a0.data/data/share/icons/hicolor/scalable/apps/vocalinux-microphone-process.svg
vocalinux-0.3.0a0.data/data/share/icons/hicolor/scalable/apps/vocalinux-microphone.svg
vocalinux-0.3.0a0.data/data/share/icons/hicolor/scalable/apps/vocalinux.svg
vocalinux-0.3.0a0.data/data/share/vocalinux/resources/icons/scalable/vocalinux-microphone-off.svg
vocalinux-0.3.0a0.data/data/share/vocalinux/resources/icons/scalable/vocalinux-microphone-process.svg
vocalinux-0.3.0a0.data/data/share/vocalinux/resources/icons/scalable/vocalinux-microphone.svg
vocalinux-0.3.0a0.data/data/share/vocalinux/resources/icons/scalable/vocalinux.svg
vocalinux-0.3.0a0.data/data/share/vocalinux/resources/sounds/error.wav
vocalinux-0.3.0a0.data/data/share/vocalinux/resources/sounds/start_recording.wav
vocalinux-0.3.0a0.data/data/share/vocalinux/resources/sounds/stop_recording.wav
vocalinux-0.3.0a0.dist-info/licenses/LICENSE
vocalinux-0.3.0a0.dist-info/METADATA
vocalinux-0.3.0a0.dist-info/WHEEL
vocalinux-0.3.0a0.dist-info/entry_points.txt
vocalinux-0.3.0a0.dist-info/top_level.txt
vocalinux-0.3.0a0.dist-info/RECORD
