Metadata-Version: 2.4
Name: vocalinux
Version: 0.3.0a0
Summary: A seamless voice dictation system for Linux
Home-page: https://github.com/jatinkrmalik/vocalinux
Author: Jatin K Malik
Author-email: Jatin K Malik <jatinkrmalik@gmail.com>
Maintainer-email: Jatin K Malik <jatinkrmalik@gmail.com>
License: GPL-3.0
Project-URL: Homepage, https://github.com/jatinkrmalik/vocalinux
Project-URL: Documentation, https://github.com/jatinkrmalik/vocalinux/tree/main/docs
Project-URL: Repository, https://github.com/jatinkrmalik/vocalinux
Project-URL: Issues, https://github.com/jatinkrmalik/vocalinux/issues
Project-URL: Changelog, https://github.com/jatinkrmalik/vocalinux/releases
Keywords: voice,dictation,speech,recognition,linux,accessibility,voice-typing,speech-to-text
Classifier: Development Status :: 3 - Alpha
Classifier: Environment :: X11 Applications :: GTK
Classifier: Intended Audience :: End Users/Desktop
Classifier: License :: OSI Approved :: GNU General Public License v3 (GPLv3)
Classifier: Operating System :: POSIX :: Linux
Classifier: Programming Language :: Python :: 3
Classifier: Programming Language :: Python :: 3.8
Classifier: Programming Language :: Python :: 3.9
Classifier: Programming Language :: Python :: 3.10
Classifier: Programming Language :: Python :: 3.11
Classifier: Programming Language :: Python :: 3.12
Classifier: Topic :: Desktop Environment :: Gnome
Classifier: Topic :: Multimedia :: Sound/Audio :: Speech
Classifier: Topic :: Text Processing
Classifier: Topic :: Utilities
Requires-Python: >=3.8
License-File: LICENSE
Requires-Dist: vosk>=0.3.45
Requires-Dist: pydub>=0.25.1
Requires-Dist: pynput>=1.7.6
Requires-Dist: requests>=2.28.0
Requires-Dist: tqdm>=4.64.0
Requires-Dist: numpy>=1.22.0
Requires-Dist: pyaudio>=0.2.13
Requires-Dist: python-xlib; sys_platform == "linux"
Requires-Dist: PyGObject; sys_platform == "linux"
Provides-Extra: whisper
Requires-Dist: openai-whisper>=20231117; extra == "whisper"
Requires-Dist: torch>=2.0.0; extra == "whisper"
Requires-Dist: torchaudio>=2.0.0; extra == "whisper"
Provides-Extra: dev
Requires-Dist: pytest>=7.0.0; extra == "dev"
Requires-Dist: pytest-cov>=4.0.0; extra == "dev"
Requires-Dist: pytest-mock>=3.10.0; extra == "dev"
Requires-Dist: black>=23.0.0; extra == "dev"
Requires-Dist: isort>=5.12.0; extra == "dev"
Requires-Dist: flake8>=6.0.0; extra == "dev"
Requires-Dist: pre-commit>=3.0.0; extra == "dev"
Requires-Dist: mypy>=1.0.0; extra == "dev"
Provides-Extra: docs
Requires-Dist: sphinx>=6.0.0; extra == "docs"
Requires-Dist: sphinx-rtd-theme>=1.2.0; extra == "docs"
Dynamic: author
Dynamic: home-page
Dynamic: license-file
Dynamic: requires-python
